{
  "id": "00a57f5d-8c5c-4ebb-9cbc-ab7ce84eb1ec",
  "prevId": "00000000-0000-0000-0000-000000000000",
  "version": "7",
  "dialect": "postgresql",
  "tables": {
    "public.stories-of-us_account": {
      "name": "stories-of-us_account",
      "schema": "",
      "columns": {
        "user_id": {
          "name": "user_id",
          "type": "varchar(255)",
          "primaryKey": false,
          "notNull": true
        },
        "provider": {
          "name": "provider",
          "type": "varchar(255)",
          "primaryKey": false,
          "notNull": true
        },
        "provider_account_id": {
          "name": "provider_account_id",
          "type": "varchar(255)",
          "primaryKey": false,
          "notNull": true
        },
        "refresh_token": {
          "name": "refresh_token",
          "type": "text",
          "primaryKey": false,
          "notNull": false
        },
        "access_token": {
          "name": "access_token",
          "type": "text",
          "primaryKey": false,
          "notNull": false
        },
        "expires_at": {
          "name": "expires_at",
          "type": "integer",
          "primaryKey": false,
          "notNull": false
        },
        "token_type": {
          "name": "token_type",
          "type": "varchar(255)",
          "primaryKey": false,
          "notNull": false
        },
        "scope": {
          "name": "scope",
          "type": "varchar(255)",
          "primaryKey": false,
          "notNull": false
        },
        "id_token": {
          "name": "id_token",
          "type": "text",
          "primaryKey": false,
          "notNull": false
        },
        "session_state": {
          "name": "session_state",
          "type": "varchar(255)",
          "primaryKey": false,
          "notNull": false
        }
      },
      "indexes": {
        "account_user_id_idx": {
          "name": "account_user_id_idx",
          "columns": [
            {
              "expression": "user_id",
              "isExpression": false,
              "asc": true,
              "nulls": "last"
            }
          ],
          "isUnique": false,
          "concurrently": false,
          "method": "btree",
          "with": {}
        }
      },
      "foreignKeys": {
        "stories-of-us_account_user_id_stories-of-us_user_id_fk": {
          "name": "stories-of-us_account_user_id_stories-of-us_user_id_fk",
          "tableFrom": "stories-of-us_account",
          "tableTo": "stories-of-us_user",
          "columnsFrom": [
            "user_id"
          ],
          "columnsTo": [
            "id"
          ],
          "onDelete": "no action",
          "onUpdate": "no action"
        }
      },
      "compositePrimaryKeys": {
        "stories-of-us_account_provider_provider_account_id_pk": {
          "name": "stories-of-us_account_provider_provider_account_id_pk",
          "columns": [
            "provider",
            "provider_account_id"
          ]
        }
      },
      "uniqueConstraints": {},
      "policies": {},
      "checkConstraints": {},
      "isRLSEnabled": false
    },
    "public.stories-of-us_comment": {
      "name": "stories-of-us_comment",
      "schema": "",
      "columns": {
        "id": {
          "name": "id",
          "type": "serial",
          "primaryKey": true,
          "notNull": true
        },
        "user_id": {
          "name": "user_id",
          "type": "varchar(255)",
          "primaryKey": false,
          "notNull": true
        },
        "story_id": {
          "name": "story_id",
          "type": "integer",
          "primaryKey": false,
          "notNull": true
        },
        "content": {
          "name": "content",
          "type": "text",
          "primaryKey": false,
          "notNull": true
        },
        "reactions": {
          "name": "reactions",
          "type": "text",
          "primaryKey": false,
          "notNull": false
        },
        "replies": {
          "name": "replies",
          "type": "integer[]",
          "primaryKey": false,
          "notNull": true,
          "default": "'{}'::integer[]"
        }
      },
      "indexes": {},
      "foreignKeys": {
        "stories-of-us_comment_user_id_stories-of-us_user_id_fk": {
          "name": "stories-of-us_comment_user_id_stories-of-us_user_id_fk",
          "tableFrom": "stories-of-us_comment",
          "tableTo": "stories-of-us_user",
          "columnsFrom": [
            "user_id"
          ],
          "columnsTo": [
            "id"
          ],
          "onDelete": "no action",
          "onUpdate": "no action"
        },
        "stories-of-us_comment_story_id_stories-of-us_story_id_fk": {
          "name": "stories-of-us_comment_story_id_stories-of-us_story_id_fk",
          "tableFrom": "stories-of-us_comment",
          "tableTo": "stories-of-us_story",
          "columnsFrom": [
            "story_id"
          ],
          "columnsTo": [
            "id"
          ],
          "onDelete": "no action",
          "onUpdate": "no action"
        }
      },
      "compositePrimaryKeys": {},
      "uniqueConstraints": {},
      "policies": {},
      "checkConstraints": {},
      "isRLSEnabled": false
    },
    "public.stories-of-us_heart": {
      "name": "stories-of-us_heart",
      "schema": "",
      "columns": {
        "id": {
          "name": "id",
          "type": "serial",
          "primaryKey": true,
          "notNull": true
        },
        "story_id": {
          "name": "story_id",
          "type": "integer",
          "primaryKey": false,
          "notNull": true
        },
        "user_id": {
          "name": "user_id",
          "type": "varchar(255)",
          "primaryKey": false,
          "notNull": true
        },
        "created_at": {
          "name": "created_at",
          "type": "timestamp with time zone",
          "primaryKey": false,
          "notNull": true,
          "default": "CURRENT_TIMESTAMP"
        }
      },
      "indexes": {},
      "foreignKeys": {
        "stories-of-us_heart_story_id_stories-of-us_story_id_fk": {
          "name": "stories-of-us_heart_story_id_stories-of-us_story_id_fk",
          "tableFrom": "stories-of-us_heart",
          "tableTo": "stories-of-us_story",
          "columnsFrom": [
            "story_id"
          ],
          "columnsTo": [
            "id"
          ],
          "onDelete": "no action",
          "onUpdate": "no action"
        },
        "stories-of-us_heart_user_id_stories-of-us_user_id_fk": {
          "name": "stories-of-us_heart_user_id_stories-of-us_user_id_fk",
          "tableFrom": "stories-of-us_heart",
          "tableTo": "stories-of-us_user",
          "columnsFrom": [
            "user_id"
          ],
          "columnsTo": [
            "id"
          ],
          "onDelete": "no action",
          "onUpdate": "no action"
        }
      },
      "compositePrimaryKeys": {},
      "uniqueConstraints": {},
      "policies": {},
      "checkConstraints": {},
      "isRLSEnabled": false
    },
    "public.stories-of-us_story": {
      "name": "stories-of-us_story",
      "schema": "",
      "columns": {
        "id": {
          "name": "id",
          "type": "serial",
          "primaryKey": true,
          "notNull": true
        },
        "name": {
          "name": "name",
          "type": "varchar(256)",
          "primaryKey": false,
          "notNull": true
        },
        "description": {
          "name": "description",
          "type": "text",
          "primaryKey": false,
          "notNull": false
        },
        "cover_image": {
          "name": "cover_image",
          "type": "varchar(255)",
          "primaryKey": false,
          "notNull": true
        },
        "images": {
          "name": "images",
          "type": "text[]",
          "primaryKey": false,
          "notNull": true,
          "default": "'{}'::text[]"
        },
        "user_id": {
          "name": "user_id",
          "type": "varchar(255)",
          "primaryKey": false,
          "notNull": true
        },
        "sort": {
          "name": "sort",
          "type": "real",
          "primaryKey": false,
          "notNull": false
        },
        "created_at": {
          "name": "created_at",
          "type": "timestamp with time zone",
          "primaryKey": false,
          "notNull": true,
          "default": "CURRENT_TIMESTAMP"
        },
        "updated_at": {
          "name": "updated_at",
          "type": "timestamp with time zone",
          "primaryKey": false,
          "notNull": false
        },
        "location": {
          "name": "location",
          "type": "varchar(256)",
          "primaryKey": false,
          "notNull": false
        },
        "location_lat": {
          "name": "location_lat",
          "type": "real",
          "primaryKey": false,
          "notNull": false
        },
        "location_lng": {
          "name": "location_lng",
          "type": "real",
          "primaryKey": false,
          "notNull": false
        },
        "feeling": {
          "name": "feeling",
          "type": "varchar(100)",
          "primaryKey": false,
          "notNull": false
        },
        "activity": {
          "name": "activity",
          "type": "varchar(100)",
          "primaryKey": false,
          "notNull": false
        },
        "privacy": {
          "name": "privacy",
          "type": "varchar(50)",
          "primaryKey": false,
          "notNull": true,
          "default": "'public'"
        },
        "background_style": {
          "name": "background_style",
          "type": "text",
          "primaryKey": false,
          "notNull": false
        },
        "mentioned_users": {
          "name": "mentioned_users",
          "type": "text[]",
          "primaryKey": false,
          "notNull": false,
          "default": "'{}'::text[]"
        },
        "scheduled_publish_time": {
          "name": "scheduled_publish_time",
          "type": "timestamp with time zone",
          "primaryKey": false,
          "notNull": false
        },
        "post_format": {
          "name": "post_format",
          "type": "varchar(50)",
          "primaryKey": false,
          "notNull": true,
          "default": "'standard'"
        }
      },
      "indexes": {},
      "foreignKeys": {},
      "compositePrimaryKeys": {},
      "uniqueConstraints": {},
      "policies": {},
      "checkConstraints": {},
      "isRLSEnabled": false
    },
    "public.stories-of-us_user": {
      "name": "stories-of-us_user",
      "schema": "",
      "columns": {
        "id": {
          "name": "id",
          "type": "varchar(255)",
          "primaryKey": true,
          "notNull": true
        },
        "name": {
          "name": "name",
          "type": "varchar(255)",
          "primaryKey": false,
          "notNull": true
        },
        "email": {
          "name": "email",
          "type": "varchar(255)",
          "primaryKey": false,
          "notNull": true
        },
        "email_verified": {
          "name": "email_verified",
          "type": "timestamp with time zone",
          "primaryKey": false,
          "notNull": false,
          "default": "CURRENT_TIMESTAMP"
        },
        "avatar": {
          "name": "avatar",
          "type": "varchar(255)",
          "primaryKey": false,
          "notNull": false
        }
      },
      "indexes": {},
      "foreignKeys": {},
      "compositePrimaryKeys": {},
      "uniqueConstraints": {},
      "policies": {},
      "checkConstraints": {},
      "isRLSEnabled": false
    }
  },
  "enums": {},
  "schemas": {},
  "sequences": {},
  "roles": {},
  "policies": {},
  "views": {},
  "_meta": {
    "columns": {},
    "schemas": {},
    "tables": {}
  }
}